{
  "female_jobs": [
    {"id":1,"job":"Cleaner","gender":"female","common_risks":["chemical exposure","physical strain"],"nutrient_risks":["vitamin C"]},
    {"id":2,"job":"Factory Worker","gender":"female","common_risks":["repetitive motion","noise"],"nutrient_risks":["magnesium"]},
    {"id":3,"job":"Warehouse Worker","gender":"female","common_risks":["lifting","physical strain"],"nutrient_risks":["magnesium"]},
    {"id":4,"job":"Delivery Driver","gender":"female","common_risks":["sitting","traffic stress"],"nutrient_risks":["vitamin D"]},
    {"id":5,"job":"Supermarket Worker","gender":"female","common_risks":["standing"],"nutrient_risks":["magnesium"]},
    {"id":6,"job":"Fast Food Worker","gender":"female","common_risks":["heat","standing"],"nutrient_risks":["magnesium"]},
    {"id":7,"job":"Kitchen Assistant","gender":"female","common_risks":["heat","physical strain"],"nutrient_risks":["magnesium"]},
    {"id":8,"job":"Dishwasher","gender":"female","common_risks":["humidity","standing"],"nutrient_risks":["magnesium"]},
    {"id":9,"job":"Street Vendor","gender":"female","common_risks":["sun exposure"],"nutrient_risks":["vitamin C"]},
    {"id":10,"job":"Market Seller","gender":"female","common_risks":["standing","weather exposure"],"nutrient_risks":["vitamin C"]},
    {"id":11,"job":"Babysitter","gender":"female","common_risks":["physical strain"],"nutrient_risks":["magnesium"]},
    {"id":12,"job":"Elderly Caregiver","gender":"female","common_risks":["physical strain","emotional stress"],"nutrient_risks":["magnesium"]},
    {"id":13,"job":"Home Care Assistant","gender":"female","common_risks":["physical strain"],"nutrient_risks":["magnesium"]},
    {"id":14,"job":"Laundry Worker","gender":"female","common_risks":["humidity","heat"],"nutrient_risks":["magnesium"]},
    {"id":15,"job":"Janitor","gender":"female","common_risks":["chemical exposure"],"nutrient_risks":["vitamin C"]},
    {"id":16,"job":"Construction Laborer","gender":"female","common_risks":["physical strain","dust"],"nutrient_risks":["magnesium"]},
    {"id":17,"job":"Painter","gender":"female","common_risks":["chemical fumes"],"nutrient_risks":["vitamin C"]},
    {"id":18,"job":"Assembler","gender":"female","common_risks":["repetitive motion"],"nutrient_risks":["magnesium"]},
    {"id":19,"job":"Machine Operator","gender":"female","common_risks":["noise","repetitive motion"],"nutrient_risks":["magnesium"]},
    {"id":20,"job":"Textile Worker","gender":"female","common_risks":["dust"],"nutrient_risks":["vitamin C"]},
    {"id":21,"job":"Farm Worker","gender":"female","common_risks":["sun exposure","physical strain"],"nutrient_risks":["vitamin C"]},
    {"id":22,"job":"Fruit Picker","gender":"female","common_risks":["sun exposure"],"nutrient_risks":["vitamin C"]},
    {"id":23,"job":"Cleaner Supervisor","gender":"female","common_risks":["stress"],"nutrient_risks":["magnesium"]},
    {"id":24,"job":"Security Officer","gender":"female","common_risks":["night shifts"],"nutrient_risks":["vitamin D"]},
    {"id":25,"job":"Parking Attendant","gender":"female","common_risks":["weather exposure"],"nutrient_risks":["vitamin C"]},
    {"id":26,"job":"Bus Driver","gender":"female","common_risks":["sitting","stress"],"nutrient_risks":["vitamin D"]},
    {"id":27,"job":"Taxi Driver","gender":"female","common_risks":["sitting","stress"],"nutrient_risks":["vitamin D"]},
    {"id":28,"job":"Train Attendant","gender":"female","common_risks":["shift work"],"nutrient_risks":["magnesium"]},
    {"id":29,"job":"Ticket Seller","gender":"female","common_risks":["sedentary"],"nutrient_risks":["vitamin D"]},
    {"id":30,"job":"Postal Worker","gender":"female","common_risks":["walking","weather exposure"],"nutrient_risks":["vitamin C"]},
    {"id":31,"job":"Courier","gender":"female","common_risks":["traffic","physical strain"],"nutrient_risks":["magnesium"]},
    {"id":32,"job":"Warehouse Picker","gender":"female","common_risks":["lifting"],"nutrient_risks":["magnesium"]},
    {"id":33,"job":"Stock Clerk","gender":"female","common_risks":["lifting","standing"],"nutrient_risks":["magnesium"]},
    {"id":34,"job":"Retail Cashier","gender":"female","common_risks":["standing"],"nutrient_risks":["magnesium"]},
    {"id":35,"job":"Shop Assistant","gender":"female","common_risks":["standing"],"nutrient_risks":["magnesium"]},
    {"id":36,"job":"Call Operator","gender":"female","common_risks":["sedentary","stress"],"nutrient_risks":["magnesium"]},
    {"id":37,"job":"Data Entry Clerk","gender":"female","common_risks":["sedentary","screen exposure"],"nutrient_risks":["omega-3"]},
    {"id":38,"job":"Reception Assistant","gender":"female","common_risks":["sedentary"],"nutrient_risks":["vitamin D"]},
    {"id":39,"job":"Office Clerk","gender":"female","common_risks":["sedentary"],"nutrient_risks":["vitamin D"]},
    {"id":40,"job":"Secretary","gender":"female","common_risks":["sedentary"],"nutrient_risks":["vitamin D"]},
    {"id":41,"job":"Personal Assistant","gender":"female","common_risks":["stress","sedentary"],"nutrient_risks":["magnesium"]},
    {"id":42,"job":"Sales Representative","gender":"female","common_risks":["travel","stress"],"nutrient_risks":["magnesium"]},
    {"id":43,"job":"Telemarketer","gender":"female","common_risks":["stress","sedentary"],"nutrient_risks":["magnesium"]},
    {"id":44,"job":"Insurance Clerk","gender":"female","common_risks":["sedentary"],"nutrient_risks":["vitamin D"]},
    {"id":45,"job":"Bank Clerk","gender":"female","common_risks":["sedentary"],"nutrient_risks":["vitamin D"]},
    {"id":46,"job":"School Assistant","gender":"female","common_risks":["standing"],"nutrient_risks":["magnesium"]},
    {"id":47,"job":"Teaching Assistant","gender":"female","common_risks":["standing"],"nutrient_risks":["magnesium"]},
    {"id":48,"job":"Daycare Assistant","gender":"female","common_risks":["infection exposure"],"nutrient_risks":["vitamin C"]},
    {"id":49,"job":"Care Assistant","gender":"female","common_risks":["physical strain"],"nutrient_risks":["magnesium"]},
    {"id":50,"job":"Hospital Cleaner","gender":"female","common_risks":["bio exposure"],"nutrient_risks":["vitamin C"]},
    {"id":101,"job":"Graphic Designer","gender":"female","common_risks":["screen exposure","sedentary"],"nutrient_risks":["omega-3","vitamin D"]},
    {"id":102,"job":"UX Designer","gender":"female","common_risks":["screen exposure"],"nutrient_risks":["omega-3"]},
    {"id":103,"job":"UI Designer","gender":"female","common_risks":["screen exposure"],"nutrient_risks":["omega-3"]},
    {"id":104,"job":"Web Designer","gender":"female","common_risks":["sedentary"],"nutrient_risks":["vitamin D"]},
    {"id":105,"job":"Animator","gender":"female","common_risks":["screen exposure"],"nutrient_risks":["omega-3"]},
    {"id":106,"job":"Photographer","gender":"female","common_risks":["screen exposure","sun exposure"],"nutrient_risks":["omega-3","vitamin C"]},
    {"id":107,"job":"Video Editor","gender":"female","common_risks":["screen exposure"],"nutrient_risks":["omega-3"]},
    {"id":108,"job":"Content Creator","gender":"female","common_risks":["screen exposure"],"nutrient_risks":["omega-3"]},
    {"id":109,"job":"Social Media Manager","gender":"female","common_risks":["sedentary","screen exposure"],"nutrient_risks":["omega-3"]},
    {"id":110,"job":"Marketing Manager","gender":"female","common_risks":["stress","sedentary"],"nutrient_risks":["magnesium"]},
    {"id":111,"job":"Brand Manager","gender":"female","common_risks":["stress"],"nutrient_risks":["magnesium"]},
    {"id":112,"job":"Advertising Specialist","gender":"female","common_risks":["stress"],"nutrient_risks":["magnesium"]},
    {"id":113,"job":"Public Relations Manager","gender":"female","common_risks":["stress","travel"],"nutrient_risks":["magnesium"]},
    {"id":114,"job":"Event Planner","gender":"female","common_risks":["stress","irregular hours"],"nutrient_risks":["magnesium"]},
    {"id":115,"job":"Wedding Planner","gender":"female","common_risks":["stress"],"nutrient_risks":["magnesium"]},
    {"id":116,"job":"Human Resources Manager","gender":"female","common_risks":["stress","sedentary"],"nutrient_risks":["magnesium"]},
    {"id":117,"job":"Recruiter","gender":"female","common_risks":["stress"],"nutrient_risks":["magnesium"]},
    {"id":118,"job":"Office Manager","gender":"female","common_risks":["sedentary"],"nutrient_risks":["vitamin D"]},
    {"id":119,"job":"Administrative Assistant","gender":"female","common_risks":["sedentary"],"nutrient_risks":["vitamin D"]},
    {"id":120,"job":"Executive Assistant","gender":"female","common_risks":["stress","sedentary"],"nutrient_risks":["magnesium"]},
    {"id":121,"job":"Receptionist","gender":"female","common_risks":["sedentary"],"nutrient_risks":["vitamin D"]},
    {"id":122,"job":"Call Center Agent","gender":"female","common_risks":["sedentary","stress"],"nutrient_risks":["magnesium"]},
    {"id":123,"job":"Customer Service Representative","gender":"female","common_risks":["stress","sedentary"],"nutrient_risks":["magnesium"]},
    {"id":124,"job":"Bank Teller","gender":"female","common_risks":["standing","stress"],"nutrient_risks":["magnesium"]},
    {"id":125,"job":"Accountant","gender":"female","common_risks":["sedentary","stress"],"nutrient_risks":["magnesium"]},
    {"id":126,"job":"Financial Analyst","gender":"female","common_risks":["sedentary"],"nutrient_risks":["vitamin D"]},
    {"id":127,"job":"Bookkeeper","gender":"female","common_risks":["sedentary"],"nutrient_risks":["vitamin D"]},
    {"id":128,"job":"Insurance Agent","gender":"female","common_risks":["stress"],"nutrient_risks":["magnesium"]},
    {"id":129,"job":"Real Estate Agent","gender":"female","common_risks":["travel","stress"],"nutrient_risks":["magnesium"]},
    {"id":130,"job":"Property Manager","gender":"female","common_risks":["stress"],"nutrient_risks":["magnesium"]},
    {"id":131,"job":"Teacher","gender":"female","common_risks":["standing","stress"],"nutrient_risks":["magnesium"]},
    {"id":132,"job":"Kindergarten Teacher","gender":"female","common_risks":["infection exposure"],"nutrient_risks":["vitamin C"]},
    {"id":133,"job":"School Counselor","gender":"female","common_risks":["emotional stress"],"nutrient_risks":["magnesium"]},
    {"id":134,"job":"Special Education Teacher","gender":"female","common_risks":["stress"],"nutrient_risks":["magnesium"]},
    {"id":135,"job":"University Lecturer","gender":"female","common_risks":["sedentary"],"nutrient_risks":["vitamin D"]},
    {"id":136,"job":"Tutor","gender":"female","common_risks":["sedentary"],"nutrient_risks":["vitamin D"]},
    {"id":137,"job":"Librarian","gender":"female","common_risks":["indoor work"],"nutrient_risks":["vitamin D"]},
    {"id":138,"job":"Archivist","gender":"female","common_risks":["dust"],"nutrient_risks":["vitamin C"]},
    {"id":139,"job":"Research Assistant","gender":"female","common_risks":["sedentary"],"nutrient_risks":["vitamin D"]},
    {"id":140,"job":"Scientist","gender":"female","common_risks":["lab chemicals"],"nutrient_risks":["vitamin C"]},
    {"id":141,"job":"Biologist","gender":"female","common_risks":["lab exposure"],"nutrient_risks":["vitamin C"]},
    {"id":142,"job":"Chemist","gender":"female","common_risks":["chemical exposure"],"nutrient_risks":["antioxidants"]},
    {"id":143,"job":"Pharmacist","gender":"female","common_risks":["standing"],"nutrient_risks":["magnesium"]},
    {"id":144,"job":"Pharmacy Technician","gender":"female","common_risks":["standing"],"nutrient_risks":["magnesium"]},
    {"id":145,"job":"Medical Laboratory Technician","gender":"female","common_risks":["bio exposure"],"nutrient_risks":["vitamin C"]},
    {"id":146,"job":"Radiology Technician","gender":"female","common_risks":["radiation"],"nutrient_risks":["antioxidants"]},
    {"id":147,"job":"Nurse Practitioner","gender":"female","common_risks":["night shifts","stress"],"nutrient_risks":["magnesium"]},
    {"id":148,"job":"Midwife","gender":"female","common_risks":["night shifts","stress"],"nutrient_risks":["magnesium"]},
    {"id":149,"job":"Paramedic","gender":"female","common_risks":["stress","night shifts"],"nutrient_risks":["magnesium"]},
    {"id":150,"job":"Ambulance Driver","gender":"female","common_risks":["stress"],"nutrient_risks":["magnesium"]},
    {"id":151,"job":"Hospital Administrator","gender":"female","common_risks":["sedentary","stress"],"nutrient_risks":["magnesium"]},
    {"id":152,"job":"Clinic Receptionist","gender":"female","common_risks":["sedentary"],"nutrient_risks":["vitamin D"]},
    {"id":153,"job":"Dental Assistant","gender":"female","common_risks":["bio exposure"],"nutrient_risks":["vitamin C"]},
    {"id":154,"job":"Dental Hygienist","gender":"female","common_risks":["bio exposure"],"nutrient_risks":["vitamin C"]},
    {"id":155,"job":"Optician","gender":"female","common_risks":["screen exposure"],"nutrient_risks":["omega-3"]},
    {"id":156,"job":"Psychologist","gender":"female","common_risks":["emotional stress"],"nutrient_risks":["magnesium"]},
    {"id":157,"job":"Therapist","gender":"female","common_risks":["emotional stress"],"nutrient_risks":["magnesium"]},
    {"id":158,"job":"Social Worker","gender":"female","common_risks":["stress"],"nutrient_risks":["magnesium"]},
    {"id":159,"job":"Childcare Worker","gender":"female","common_risks":["infection exposure"],"nutrient_risks":["vitamin C"]},
    {"id":160,"job":"Nanny","gender":"female","common_risks":["physical strain"],"nutrient_risks":["magnesium"]},
    {"id":161,"job":"Housekeeper","gender":"female","common_risks":["cleaning chemicals"],"nutrient_risks":["vitamin C"]},
    {"id":162,"job":"Hotel Receptionist","gender":"female","common_risks":["shift work"],"nutrient_risks":["magnesium"]},
    {"id":163,"job":"Flight Attendant","gender":"female","common_risks":["jet lag","dehydration"],"nutrient_risks":["magnesium","vitamin C"]},
    {"id":164,"job":"Travel Agent","gender":"female","common_risks":["sedentary"],"nutrient_risks":["vitamin D"]},
    {"id":165,"job":"Tour Guide","gender":"female","common_risks":["walking","sun exposure"],"nutrient_risks":["vitamin C"]},
    {"id":166,"job":"Restaurant Manager","gender":"female","common_risks":["stress","standing"],"nutrient_risks":["magnesium"]},
    {"id":167,"job":"Chef","gender":"female","common_risks":["heat","long hours"],"nutrient_risks":["magnesium"]},
    {"id":168,"job":"Cook","gender":"female","common_risks":["heat"],"nutrient_risks":["magnesium"]},
    {"id":169,"job":"Baker","gender":"female","common_risks":["flour dust"],"nutrient_risks":["vitamin C"]},
    {"id":170,"job":"Barista","gender":"female","common_risks":["standing"],"nutrient_risks":["magnesium"]},
    {"id":171,"job":"Waitress","gender":"female","common_risks":["standing"],"nutrient_risks":["magnesium"]},
    {"id":172,"job":"Bartender","gender":"female","common_risks":["night shifts"],"nutrient_risks":["magnesium"]},
    {"id":173,"job":"Retail Manager","gender":"female","common_risks":["standing","stress"],"nutrient_risks":["magnesium"]},
    {"id":174,"job":"Sales Associate","gender":"female","common_risks":["standing"],"nutrient_risks":["magnesium"]},
    {"id":175,"job":"Cashier","gender":"female","common_risks":["standing"],"nutrient_risks":["magnesium"]},
    {"id":176,"job":"Fashion Designer","gender":"female","common_risks":["sedentary"],"nutrient_risks":["vitamin D"]},
    {"id":177,"job":"Tailor","gender":"female","common_risks":["sedentary"],"nutrient_risks":["vitamin D"]},
    {"id":178,"job":"Jewelry Designer","gender":"female","common_risks":["fine motor strain"],"nutrient_risks":["magnesium"]},
    {"id":179,"job":"Makeup Artist","gender":"female","common_risks":["chemical exposure"],"nutrient_risks":["vitamin C"]},
    {"id":180,"job":"Hairdresser","gender":"female","common_risks":["chemical exposure"],"nutrient_risks":["vitamin C"]},
    {"id":181,"job":"Nail Technician","gender":"female","common_risks":["chemical fumes"],"nutrient_risks":["vitamin C"]},
    {"id":182,"job":"Esthetician","gender":"female","common_risks":["chemical exposure"],"nutrient_risks":["vitamin C"]},
    {"id":183,"job":"Massage Therapist","gender":"female","common_risks":["physical strain"],"nutrient_risks":["magnesium"]},
    {"id":184,"job":"Yoga Instructor","gender":"female","common_risks":["physical strain"],"nutrient_risks":["magnesium"]},
    {"id":185,"job":"Pilates Instructor","gender":"female","common_risks":["physical strain"],"nutrient_risks":["magnesium"]},
    {"id":186,"job":"Fitness Trainer","gender":"female","common_risks":["physical strain"],"nutrient_risks":["magnesium","iron"]},
    {"id":187,"job":"Dance Instructor","gender":"female","common_risks":["physical strain"],"nutrient_risks":["magnesium"]},
    {"id":188,"job":"Actress","gender":"female","common_risks":["stress"],"nutrient_risks":["magnesium"]},
    {"id":189,"job":"Singer","gender":"female","common_risks":["night shifts"],"nutrient_risks":["magnesium"]},
    {"id":190,"job":"Musician","gender":"female","common_risks":["noise"],"nutrient_risks":["magnesium"]},
    {"id":191,"job":"Journalist","gender":"female","common_risks":["stress","travel"],"nutrient_risks":["magnesium"]},
    {"id":192,"job":"Editor","gender":"female","common_risks":["sedentary"],"nutrient_risks":["vitamin D"]},
    {"id":193,"job":"Writer","gender":"female","common_risks":["sedentary"],"nutrient_risks":["vitamin D"]},
    {"id":194,"job":"Translator","gender":"female","common_risks":["sedentary"],"nutrient_risks":["vitamin D"]},
    {"id":195,"job":"Proofreader","gender":"female","common_risks":["sedentary"],"nutrient_risks":["vitamin D"]},
    {"id":196,"job":"Life Coach","gender":"female","common_risks":["emotional stress"],"nutrient_risks":["magnesium"]},
    {"id":197,"job":"Career Coach","gender":"female","common_risks":["stress"],"nutrient_risks":["magnesium"]},
    {"id":198,"job":"Nutrition Coach","gender":"female","common_risks":["stress"],"nutrient_risks":["magnesium"]},
    {"id":199,"job":"Dietitian","gender":"female","common_risks":["standing"],"nutrient_risks":["magnesium"]},
    {"id":200,"job":"Public Health Specialist","gender":"female","common_risks":["stress"],"nutrient_risks":["magnesium"]},
    {"id":201,"job":"Epidemiologist","gender":"female","common_risks":["sedentary"],"nutrient_risks":["vitamin D"]},
    {"id":202,"job":"Environmental Scientist","gender":"female","common_risks":["field exposure"],"nutrient_risks":["vitamin C"]},
    {"id":203,"job":"Geologist","gender":"female","common_risks":["field exposure"],"nutrient_risks":["vitamin C"]},
    {"id":204,"job":"Meteorologist","gender":"female","common_risks":["night shifts"],"nutrient_risks":["magnesium"]},
    {"id":205,"job":"Urban Planner","gender":"female","common_risks":["sedentary"],"nutrient_risks":["vitamin D"]},
    {"id":206,"job":"Architect","gender":"female","common_risks":["sedentary","stress"],"nutrient_risks":["magnesium"]},
    {"id":207,"job":"Interior Designer","gender":"female","common_risks":["chemical exposure"],"nutrient_risks":["vitamin C"]},
    {"id":208,"job":"Landscape Designer","gender":"female","common_risks":["sun exposure"],"nutrient_risks":["vitamin C"]},
    {"id":209,"job":"Civil Engineer","gender":"female","common_risks":["stress"],"nutrient_risks":["magnesium"]},
    {"id":210,"job":"Mechanical Engineer","gender":"female","common_risks":["noise","stress"],"nutrient_risks":["magnesium"]},
    {"id":211,"job":"Electrical Engineer","gender":"female","common_risks":["screen exposure"],"nutrient_risks":["omega-3"]},
    {"id":212,"job":"Software Engineer","gender":"female","common_risks":["sedentary","screen exposure"],"nutrient_risks":["omega-3"]},
    {"id":213,"job":"Data Scientist","gender":"female","common_risks":["sedentary","screen exposure"],"nutrient_risks":["omega-3"]},
    {"id":214,"job":"AI Engineer","gender":"female","common_risks":["sedentary"],"nutrient_risks":["omega-3"]},
    {"id":215,"job":"Cybersecurity Analyst","gender":"female","common_risks":["screen exposure"],"nutrient_risks":["omega-3"]},
    {"id":216,"job":"Database Administrator","gender":"female","common_risks":["sedentary"],"nutrient_risks":["vitamin D"]},
    {"id":217,"job":"IT Support Specialist","gender":"female","common_risks":["sedentary"],"nutrient_risks":["vitamin D"]},
    {"id":218,"job":"Network Administrator","gender":"female","common_risks":["screen exposure"],"nutrient_risks":["omega-3"]},
    {"id":219,"job":"Cloud Engineer","gender":"female","common_risks":["sedentary"],"nutrient_risks":["vitamin D"]},
    {"id":220,"job":"DevOps Engineer","gender":"female","common_risks":["sedentary"],"nutrient_risks":["vitamin D"]},
    {"id":221,"job":"Startup Founder","gender":"female","common_risks":["high stress"],"nutrient_risks":["magnesium"]},
    {"id":222,"job":"Entrepreneur","gender":"female","common_risks":["stress"],"nutrient_risks":["magnesium"]},
    {"id":223,"job":"Business Consultant","gender":"female","common_risks":["travel","stress"],"nutrient_risks":["magnesium"]},
    {"id":224,"job":"Management Consultant","gender":"female","common_risks":["travel","stress"],"nutrient_risks":["magnesium"]},
    {"id":225,"job":"Project Manager","gender":"female","common_risks":["stress"],"nutrient_risks":["magnesium"]},
    {"id":226,"job":"Product Manager","gender":"female","common_risks":["stress"],"nutrient_risks":["magnesium"]},
    {"id":227,"job":"Operations Manager","gender":"female","common_risks":["stress"],"nutrient_risks":["magnesium"]},
    {"id":228,"job":"Supply Chain Manager","gender":"female","common_risks":["stress"],"nutrient_risks":["magnesium"]},
    {"id":229,"job":"Logistics Coordinator","gender":"female","common_risks":["stress"],"nutrient_risks":["magnesium"]},
    {"id":230,"job":"Warehouse Manager","gender":"female","common_risks":["stress"],"nutrient_risks":["magnesium"]},
    {"id":231,"job":"Customs Officer","gender":"female","common_risks":["shift work"],"nutrient_risks":["vitamin D"]},
    {"id":232,"job":"Police Officer","gender":"female","common_risks":["stress","shift work"],"nutrient_risks":["magnesium"]},
    {"id":233,"job":"Firefighter","gender":"female","common_risks":["smoke exposure"],"nutrient_risks":["vitamin C"]},
    {"id":234,"job":"Security Guard","gender":"female","common_risks":["night shifts"],"nutrient_risks":["vitamin D"]},
    {"id":235,"job":"Military Officer","gender":"female","common_risks":["stress"],"nutrient_risks":["magnesium"]},
    {"id":236,"job":"Judge","gender":"female","common_risks":["sedentary","stress"],"nutrient_risks":["magnesium"]},
    {"id":237,"job":"Lawyer","gender":"female","common_risks":["sedentary","stress"],"nutrient_risks":["magnesium"]},
    {"id":238,"job":"Paralegal","gender":"female","common_risks":["sedentary"],"nutrient_risks":["vitamin D"]},
    {"id":239,"job":"Court Clerk","gender":"female","common_risks":["sedentary"],"nutrient_risks":["vitamin D"]},
    {"id":240,"job":"Notary","gender":"female","common_risks":["sedentary"],"nutrient_risks":["vitamin D"]},
    {"id":241,"job":"Historian","gender":"female","common_risks":["sedentary"],"nutrient_risks":["vitamin D"]},
    {"id":242,"job":"Archaeologist","gender":"female","common_risks":["sun exposure","dust"],"nutrient_risks":["vitamin C"]},
    {"id":243,"job":"Anthropologist","gender":"female","common_risks":["travel"],"nutrient_risks":["magnesium"]},
    {"id":244,"job":"Philosopher","gender":"female","common_risks":["sedentary"],"nutrient_risks":["vitamin D"]},
    {"id":245,"job":"Theologian","gender":"female","common_risks":["sedentary"],"nutrient_risks":["vitamin D"]},
    {"id":246,"job":"Priest","gender":"female","common_risks":["stress"],"nutrient_risks":["magnesium"]},
    {"id":247,"job":"Spiritual Counselor","gender":"female","common_risks":["emotional stress"],"nutrient_risks":["magnesium"]},
    {"id":248,"job":"Meditation Teacher","gender":"female","common_risks":["sedentary"],"nutrient_risks":["vitamin D"]},
    {"id":249,"job":"Parenting Coach","gender":"female","common_risks":["stress"],"nutrient_risks":["magnesium"]},
    {"id":250,"job":"Birth Preparation Coach","gender":"female","common_risks":["irregular hours"],"nutrient_risks":["magnesium"]},
    {"id":251,"job":"Fertility Coach","gender":"female","common_risks":["stress"],"nutrient_risks":["magnesium"]},
    {"id":252,"job":"Doula","gender":"female","common_risks":["night shifts","stress"],"nutrient_risks":["magnesium"]},
    {"id":253,"job":"Baby Sleep Consultant","gender":"female","common_risks":["irregular hours"],"nutrient_risks":["magnesium"]},
    {"id":254,"job":"Lactation Consultant","gender":"female","common_risks":["stress"],"nutrient_risks":["magnesium"]},
    {"id":255,"job":"Maternal Health Educator","gender":"female","common_risks":["stress"],"nutrient_risks":["magnesium"]},
    {"id":256,"job":"Nutrition Researcher","gender":"female","common_risks":["sedentary"],"nutrient_risks":["vitamin D"]},
    {"id":257,"job":"Food Scientist","gender":"female","common_risks":["lab exposure"],"nutrient_risks":["vitamin C"]},
    {"id":258,"job":"Quality Food Inspector","gender":"female","common_risks":["standing"],"nutrient_risks":["magnesium"]},
    {"id":259,"job":"Agricultural Scientist","gender":"female","common_risks":["sun exposure"],"nutrient_risks":["vitamin C"]},
    {"id":260,"job":"Farm Manager","gender":"female","common_risks":["physical strain"],"nutrient_risks":["magnesium"]},
    {"id":261,"job":"Gardener","gender":"female","common_risks":["sun exposure"],"nutrient_risks":["vitamin C"]},
    {"id":262,"job":"Florist","gender":"female","common_risks":["standing"],"nutrient_risks":["magnesium"]},
    {"id":263,"job":"Pet Groomer","gender":"female","common_risks":["allergens"],"nutrient_risks":["vitamin C"]},
    {"id":264,"job":"Veterinary Assistant","gender":"female","common_risks":["animal exposure"],"nutrient_risks":["vitamin C"]},
    {"id":265,"job":"Zoo Keeper","gender":"female","common_risks":["bio exposure"],"nutrient_risks":["vitamin C"]},
    {"id":266,"job":"Wildlife Ranger","gender":"female","common_risks":["outdoor exposure"],"nutrient_risks":["vitamin C"]},
    {"id":267,"job":"Park Ranger","gender":"female","common_risks":["outdoor exposure"],"nutrient_risks":["vitamin C"]},
    {"id":268,"job":"Marine Biologist","gender":"female","common_risks":["field exposure"],"nutrient_risks":["vitamin C"]},
    {"id":269,"job":"Oceanographer","gender":"female","common_risks":["travel"],"nutrient_risks":["magnesium"]},
    {"id":270,"job":"Climate Researcher","gender":"female","common_risks":["sedentary"],"nutrient_risks":["vitamin D"]},
    {"id":271,"job":"Renewable Energy Consultant","gender":"female","common_risks":["travel"],"nutrient_risks":["magnesium"]},
    {"id":272,"job":"Solar Engineer","gender":"female","common_risks":["sun exposure"],"nutrient_risks":["vitamin C"]},
    {"id":273,"job":"Wind Energy Planner","gender":"female","common_risks":["travel"],"nutrient_risks":["magnesium"]},
    {"id":274,"job":"Energy Analyst","gender":"female","common_risks":["sedentary"],"nutrient_risks":["vitamin D"]},
    {"id":275,"job":"Battery Technician","gender":"female","common_risks":["chemical exposure"],"nutrient_risks":["vitamin C"]},
    {"id":276,"job":"Electronics Technician","gender":"female","common_risks":["solder fumes"],"nutrient_risks":["vitamin C"]},
    {"id":277,"job":"Computer Repair Technician","gender":"female","common_risks":["sedentary"],"nutrient_risks":["vitamin D"]},
    {"id":278,"job":"Phone Repair Technician","gender":"female","common_risks":["screen exposure"],"nutrient_risks":["omega-3"]},
    {"id":279,"job":"Appliance Technician","gender":"female","common_risks":["lifting"],"nutrient_risks":["magnesium"]},
    {"id":280,"job":"Furniture Maker","gender":"female","common_risks":["wood dust"],"nutrient_risks":["vitamin C"]},
    {"id":281,"job":"Cabinet Maker","gender":"female","common_risks":["dust"],"nutrient_risks":["vitamin C"]},
    {"id":282,"job":"Textile Machine Operator","gender":"female","common_risks":["dust"],"nutrient_risks":["vitamin C"]},
    {"id":283,"job":"Clothing Manufacturer","gender":"female","common_risks":["sedentary"],"nutrient_risks":["vitamin D"]},
    {"id":284,"job":"Jewelry Maker","gender":"female","common_risks":["fine motor strain"],"nutrient_risks":["magnesium"]},
    {"id":285,"job":"Pottery Artist","gender":"female","common_risks":["dust"],"nutrient_risks":["vitamin C"]},
    {"id":286,"job":"Ceramics Designer","gender":"female","common_risks":["dust"],"nutrient_risks":["vitamin C"]},
    {"id":287,"job":"Glass Artist","gender":"female","common_risks":["heat"],"nutrient_risks":["magnesium"]},
    {"id":288,"job":"Illustrator","gender":"female","common_risks":["sedentary"],"nutrient_risks":["vitamin D"]},
    {"id":289,"job":"Comic Artist","gender":"female","common_risks":["screen exposure"],"nutrient_risks":["omega-3"]},
    {"id":290,"job":"Game Artist","gender":"female","common_risks":["screen exposure"],"nutrient_risks":["omega-3"]},
    {"id":291,"job":"Stage Actress","gender":"female","common_risks":["stress"],"nutrient_risks":["magnesium"]},
    {"id":292,"job":"Theater Director","gender":"female","common_risks":["stress"],"nutrient_risks":["magnesium"]},
    {"id":293,"job":"Costume Designer","gender":"female","common_risks":["sedentary"],"nutrient_risks":["vitamin D"]},
    {"id":294,"job":"Set Designer","gender":"female","common_risks":["dust"],"nutrient_risks":["vitamin C"]},
    {"id":295,"job":"Lighting Designer","gender":"female","common_risks":["night shifts"],"nutrient_risks":["magnesium"]},
    {"id":296,"job":"Sound Engineer","gender":"female","common_risks":["noise"],"nutrient_risks":["magnesium"]},
    {"id":297,"job":"Music Producer","gender":"female","common_risks":["noise"],"nutrient_risks":["magnesium"]},
    {"id":298,"job":"DJ","gender":"female","common_risks":["night shifts"],"nutrient_risks":["magnesium"]},
    {"id":299,"job":"Podcast Host","gender":"female","common_risks":["sedentary"],"nutrient_risks":["vitamin D"]},
    {"id":300,"job":"Radio Host","gender":"female","common_risks":["night shifts"],"nutrient_risks":["magnesium"]},
    {"id":301,"job":"Content Strategist","gender":"female","common_risks":["screen exposure","sedentary"],"nutrient_risks":["omega-3"]},
    {"id":302,"job":"SEO Specialist","gender":"female","common_risks":["screen exposure"],"nutrient_risks":["omega-3"]},
    {"id":303,"job":"Digital Marketing Specialist","gender":"female","common_risks":["screen exposure","stress"],"nutrient_risks":["magnesium"]},
    {"id":304,"job":"Affiliate Marketing Manager","gender":"female","common_risks":["screen exposure"],"nutrient_risks":["omega-3"]},
    {"id":305,"job":"Email Marketing Specialist","gender":"female","common_risks":["sedentary"],"nutrient_risks":["vitamin D"]},
    {"id":306,"job":"E-commerce Manager","gender":"female","common_risks":["screen exposure","stress"],"nutrient_risks":["magnesium"]},
    {"id":307,"job":"Online Store Owner","gender":"female","common_risks":["sedentary","stress"],"nutrient_risks":["magnesium"]},
    {"id":308,"job":"Dropshipping Entrepreneur","gender":"female","common_risks":["screen exposure"],"nutrient_risks":["omega-3"]},
    {"id":309,"job":"Influencer","gender":"female","common_risks":["screen exposure","stress"],"nutrient_risks":["omega-3"]},
    {"id":310,"job":"Blogger","gender":"female","common_risks":["sedentary","screen exposure"],"nutrient_risks":["omega-3"]},
    {"id":311,"job":"Podcast Producer","gender":"female","common_risks":["noise","screen exposure"],"nutrient_risks":["magnesium"]},
    {"id":312,"job":"Video Producer","gender":"female","common_risks":["screen exposure"],"nutrient_risks":["omega-3"]},
    {"id":313,"job":"Film Producer","gender":"female","common_risks":["stress","long hours"],"nutrient_risks":["magnesium"]},
    {"id":314,"job":"Casting Director","gender":"female","common_risks":["stress"],"nutrient_risks":["magnesium"]},
    {"id":315,"job":"Talent Manager","gender":"female","common_risks":["stress","travel"],"nutrient_risks":["magnesium"]},
    {"id":316,"job":"Stage Manager","gender":"female","common_risks":["night shifts"],"nutrient_risks":["magnesium"]},
    {"id":317,"job":"Event Host","gender":"female","common_risks":["standing","stress"],"nutrient_risks":["magnesium"]},
    {"id":318,"job":"Conference Organizer","gender":"female","common_risks":["stress"],"nutrient_risks":["magnesium"]},
    {"id":319,"job":"Trade Show Coordinator","gender":"female","common_risks":["travel","stress"],"nutrient_risks":["magnesium"]},
    {"id":320,"job":"Community Manager","gender":"female","common_risks":["screen exposure"],"nutrient_risks":["omega-3"]},
    {"id":321,"job":"NGO Coordinator","gender":"female","common_risks":["stress"],"nutrient_risks":["magnesium"]},
    {"id":322,"job":"Charity Manager","gender":"female","common_risks":["stress"],"nutrient_risks":["magnesium"]},
    {"id":323,"job":"Volunteer Coordinator","gender":"female","common_risks":["stress"],"nutrient_risks":["magnesium"]},
    {"id":324,"job":"Humanitarian Worker","gender":"female","common_risks":["travel","stress"],"nutrient_risks":["magnesium"]},
    {"id":325,"job":"Refugee Support Worker","gender":"female","common_risks":["emotional stress"],"nutrient_risks":["magnesium"]},
    {"id":326,"job":"Youth Worker","gender":"female","common_risks":["emotional stress"],"nutrient_risks":["magnesium"]},
    {"id":327,"job":"Substance Abuse Counselor","gender":"female","common_risks":["emotional stress"],"nutrient_risks":["magnesium"]},
    {"id":328,"job":"Family Counselor","gender":"female","common_risks":["emotional stress"],"nutrient_risks":["magnesium"]},
    {"id":329,"job":"Marriage Counselor","gender":"female","common_risks":["emotional stress"],"nutrient_risks":["magnesium"]},
    {"id":330,"job":"School Psychologist","gender":"female","common_risks":["stress"],"nutrient_risks":["magnesium"]},
    {"id":331,"job":"Speech Therapist","gender":"female","common_risks":["standing"],"nutrient_risks":["magnesium"]},
    {"id":332,"job":"Occupational Therapist","gender":"female","common_risks":["physical strain"],"nutrient_risks":["magnesium"]},
    {"id":333,"job":"Physiotherapist","gender":"female","common_risks":["physical strain"],"nutrient_risks":["magnesium"]},
    {"id":334,"job":"Rehabilitation Specialist","gender":"female","common_risks":["physical strain"],"nutrient_risks":["magnesium"]},
    {"id":335,"job":"Chiropractor","gender":"female","common_risks":["physical strain"],"nutrient_risks":["magnesium"]},
    {"id":336,"job":"Acupuncturist","gender":"female","common_risks":["standing"],"nutrient_risks":["magnesium"]},
    {"id":337,"job":"Holistic Health Practitioner","gender":"female","common_risks":["stress"],"nutrient_risks":["magnesium"]},
    {"id":338,"job":"Herbalist","gender":"female","common_risks":["plant allergens"],"nutrient_risks":["vitamin C"]},
    {"id":339,"job":"Homeopath","gender":"female","common_risks":["stress"],"nutrient_risks":["magnesium"]},
    {"id":340,"job":"Wellness Coach","gender":"female","common_risks":["stress"],"nutrient_risks":["magnesium"]},
    {"id":341,"job":"Spa Manager","gender":"female","common_risks":["standing","stress"],"nutrient_risks":["magnesium"]},
    {"id":342,"job":"Sauna Attendant","gender":"female","common_risks":["heat exposure"],"nutrient_risks":["magnesium"]},
    {"id":343,"job":"Thermal Bath Attendant","gender":"female","common_risks":["humidity"],"nutrient_risks":["magnesium"]},
    {"id":344,"job":"Resort Manager","gender":"female","common_risks":["stress","travel"],"nutrient_risks":["magnesium"]},
    {"id":345,"job":"Cruise Ship Staff","gender":"female","common_risks":["shift work"],"nutrient_risks":["magnesium"]},
    {"id":346,"job":"Tourism Consultant","gender":"female","common_risks":["travel"],"nutrient_risks":["magnesium"]},
    {"id":347,"job":"Language Teacher","gender":"female","common_risks":["standing"],"nutrient_risks":["magnesium"]},
    {"id":348,"job":"Sign Language Interpreter","gender":"female","common_risks":["repetitive motion"],"nutrient_risks":["magnesium"]},
    {"id":349,"job":"Cultural Mediator","gender":"female","common_risks":["stress"],"nutrient_risks":["magnesium"]},
    {"id":350,"job":"Museum Guide","gender":"female","common_risks":["standing"],"nutrient_risks":["magnesium"]},
    {"id":351,"job":"Museum Curator","gender":"female","common_risks":["sedentary"],"nutrient_risks":["vitamin D"]},
    {"id":352,"job":"Art Restorer","gender":"female","common_risks":["chemical exposure"],"nutrient_risks":["vitamin C"]},
    {"id":353,"job":"Art Dealer","gender":"female","common_risks":["travel"],"nutrient_risks":["magnesium"]},
    {"id":354,"job":"Gallery Owner","gender":"female","common_risks":["stress"],"nutrient_risks":["magnesium"]},
    {"id":355,"job":"Auction House Specialist","gender":"female","common_risks":["stress"],"nutrient_risks":["magnesium"]},
    {"id":356,"job":"Antique Dealer","gender":"female","common_risks":["dust exposure"],"nutrient_risks":["vitamin C"]},
    {"id":357,"job":"Collector Advisor","gender":"female","common_risks":["travel"],"nutrient_risks":["magnesium"]},
    {"id":358,"job":"Luxury Brand Consultant","gender":"female","common_risks":["stress"],"nutrient_risks":["magnesium"]},
    {"id":359,"job":"Perfume Specialist","gender":"female","common_risks":["chemical exposure"],"nutrient_risks":["vitamin C"]},
    {"id":360,"job":"Cosmetics Product Developer","gender":"female","common_risks":["chemical exposure"],"nutrient_risks":["vitamin C"]},
    {"id":361,"job":"Beauty Product Tester","gender":"female","common_risks":["chemical exposure"],"nutrient_risks":["vitamin C"]},
    {"id":362,"job":"Skincare Consultant","gender":"female","common_risks":["chemical exposure"],"nutrient_risks":["vitamin C"]},
    {"id":363,"job":"Dermatology Assistant","gender":"female","common_risks":["bio exposure"],"nutrient_risks":["vitamin C"]},
    {"id":364,"job":"Medical Secretary","gender":"female","common_risks":["sedentary"],"nutrient_risks":["vitamin D"]},
    {"id":365,"job":"Hospital Scheduler","gender":"female","common_risks":["stress"],"nutrient_risks":["magnesium"]},
    {"id":366,"job":"Health Insurance Advisor","gender":"female","common_risks":["sedentary"],"nutrient_risks":["vitamin D"]},
    {"id":367,"job":"Medical Billing Specialist","gender":"female","common_risks":["screen exposure"],"nutrient_risks":["omega-3"]},
    {"id":368,"job":"Clinical Trial Coordinator","gender":"female","common_risks":["stress"],"nutrient_risks":["magnesium"]},
    {"id":369,"job":"Biotech Researcher","gender":"female","common_risks":["lab exposure"],"nutrient_risks":["vitamin C"]},
    {"id":370,"job":"Genetics Researcher","gender":"female","common_risks":["lab exposure"],"nutrient_risks":["vitamin C"]},
    {"id":371,"job":"Laboratory Manager","gender":"female","common_risks":["chemical exposure"],"nutrient_risks":["vitamin C"]},
    {"id":372,"job":"Quality Control Analyst","gender":"female","common_risks":["lab exposure"],"nutrient_risks":["vitamin C"]},
    {"id":373,"job":"Industrial Designer","gender":"female","common_risks":["sedentary"],"nutrient_risks":["vitamin D"]},
    {"id":374,"job":"Product Designer","gender":"female","common_risks":["screen exposure"],"nutrient_risks":["omega-3"]},
    {"id":375,"job":"Packaging Designer","gender":"female","common_risks":["chemical exposure"],"nutrient_risks":["vitamin C"]},
    {"id":376,"job":"Toy Designer","gender":"female","common_risks":["sedentary"],"nutrient_risks":["vitamin D"]},
    {"id":377,"job":"Game Designer","gender":"female","common_risks":["screen exposure"],"nutrient_risks":["omega-3"]},
    {"id":378,"job":"Board Game Creator","gender":"female","common_risks":["sedentary"],"nutrient_risks":["vitamin D"]},
    {"id":379,"job":"Puzzle Designer","gender":"female","common_risks":["sedentary"],"nutrient_risks":["vitamin D"]},
    {"id":380,"job":"Children's Book Author","gender":"female","common_risks":["sedentary"],"nutrient_risks":["vitamin D"]},
    {"id":381,"job":"Education Content Creator","gender":"female","common_risks":["screen exposure"],"nutrient_risks":["omega-3"]},
    {"id":382,"job":"Online Course Instructor","gender":"female","common_risks":["screen exposure"],"nutrient_risks":["omega-3"]},
    {"id":383,"job":"E-learning Developer","gender":"female","common_risks":["screen exposure"],"nutrient_risks":["omega-3"]},
    {"id":384,"job":"Instructional Designer","gender":"female","common_risks":["screen exposure"],"nutrient_risks":["omega-3"]},
    {"id":385,"job":"Education Consultant","gender":"female","common_risks":["travel","stress"],"nutrient_risks":["magnesium"]},
    {"id":386,"job":"School Principal","gender":"female","common_risks":["stress"],"nutrient_risks":["magnesium"]},
    {"id":387,"job":"Academic Advisor","gender":"female","common_risks":["sedentary"],"nutrient_risks":["vitamin D"]},
    {"id":388,"job":"Student Counselor","gender":"female","common_risks":["emotional stress"],"nutrient_risks":["magnesium"]},
    {"id":389,"job":"Dormitory Manager","gender":"female","common_risks":["stress"],"nutrient_risks":["magnesium"]},
    {"id":390,"job":"Exam Coordinator","gender":"female","common_risks":["stress"],"nutrient_risks":["magnesium"]},
    {"id":391,"job":"Voting Clerk","gender":"female","common_risks":["sedentary"],"nutrient_risks":["vitamin D"]},
    {"id":392,"job":"City Administrator","gender":"female","common_risks":["stress"],"nutrient_risks":["magnesium"]},
    {"id":393,"job":"Policy Analyst","gender":"female","common_risks":["sedentary","stress"],"nutrient_risks":["magnesium"]},
    {"id":394,"job":"Diplomatic Assistant","gender":"female","common_risks":["travel","stress"],"nutrient_risks":["magnesium"]},
    {"id":395,"job":"Embassy Staff Member","gender":"female","common_risks":["travel"],"nutrient_risks":["magnesium"]},
    {"id":396,"job":"International Aid Coordinator","gender":"female","common_risks":["travel","stress"],"nutrient_risks":["magnesium"]},
    {"id":397,"job":"Peace Program Coordinator","gender":"female","common_risks":["stress"],"nutrient_risks":["magnesium"]},
    {"id":398,"job":"Climate Policy Advisor","gender":"female","common_risks":["sedentary"],"nutrient_risks":["vitamin D"]},
    {"id":399,"job":"Sustainability Consultant","gender":"female","common_risks":["travel"],"nutrient_risks":["magnesium"]},
    {"id":400,"job":"Green Business Advisor","gender":"female","common_risks":["stress"],"nutrient_risks":["magnesium"]},
    {"id":401,"job":"Circular Economy Consultant","gender":"female","common_risks":["travel"],"nutrient_risks":["magnesium"]},
    {"id":402,"job":"Waste Management Specialist","gender":"female","common_risks":["chemical exposure"],"nutrient_risks":["vitamin C"]},
    {"id":403,"job":"Recycling Plant Supervisor","gender":"female","common_risks":["dust"],"nutrient_risks":["vitamin C"]},
    {"id":404,"job":"Environmental Educator","gender":"female","common_risks":["outdoor exposure"],"nutrient_risks":["vitamin C"]},
    {"id":405,"job":"Nature Guide","gender":"female","common_risks":["sun exposure"],"nutrient_risks":["vitamin C"]},
    {"id":406,"job":"Adventure Tour Leader","gender":"female","common_risks":["physical strain"],"nutrient_risks":["magnesium"]},
    {"id":407,"job":"Mountain Guide","gender":"female","common_risks":["physical strain","altitude"],"nutrient_risks":["magnesium"]},
    {"id":408,"job":"Ski Instructor","gender":"female","common_risks":["cold exposure"],"nutrient_risks":["vitamin D"]},
    {"id":409,"job":"Surf Instructor","gender":"female","common_risks":["sun exposure"],"nutrient_risks":["vitamin C"]},
    {"id":410,"job":"Diving Instructor","gender":"female","common_risks":["pressure exposure"],"nutrient_risks":["magnesium"]},
    {"id":411,"job":"Lifeguard","gender":"female","common_risks":["sun exposure"],"nutrient_risks":["vitamin C"]},
    {"id":412,"job":"Sports Referee","gender":"female","common_risks":["physical strain"],"nutrient_risks":["magnesium"]},
    {"id":413,"job":"Athletics Coach","gender":"female","common_risks":["physical strain"],"nutrient_risks":["magnesium"]},
    {"id":414,"job":"Gym Manager","gender":"female","common_risks":["stress"],"nutrient_risks":["magnesium"]},
    {"id":415,"job":"Sports Club Administrator","gender":"female","common_risks":["sedentary"],"nutrient_risks":["vitamin D"]},
    {"id":416,"job":"Sports Event Organizer","gender":"female","common_risks":["stress"],"nutrient_risks":["magnesium"]},
    {"id":417,"job":"Olympic Committee Staff","gender":"female","common_risks":["stress","travel"],"nutrient_risks":["magnesium"]},
    {"id":418,"job":"Sports Journalist","gender":"female","common_risks":["travel","stress"],"nutrient_risks":["magnesium"]},
    {"id":419,"job":"Sports Photographer","gender":"female","common_risks":["sun exposure"],"nutrient_risks":["vitamin C"]},
    {"id":420,"job":"Sports Commentator","gender":"female","common_risks":["stress"],"nutrient_risks":["magnesium"]},
    {"id":421,"job":"Fashion Stylist","gender":"female","common_risks":["standing"],"nutrient_risks":["magnesium"]},
    {"id":422,"job":"Personal Shopper","gender":"female","common_risks":["standing","travel"],"nutrient_risks":["magnesium"]},
    {"id":423,"job":"Wardrobe Consultant","gender":"female","common_risks":["standing"],"nutrient_risks":["magnesium"]},
    {"id":424,"job":"Costume Stylist","gender":"female","common_risks":["standing"],"nutrient_risks":["magnesium"]},
    {"id":425,"job":"Runway Coordinator","gender":"female","common_risks":["stress"],"nutrient_risks":["magnesium"]},
    {"id":426,"job":"Fashion Buyer","gender":"female","common_risks":["travel"],"nutrient_risks":["magnesium"]},
    {"id":427,"job":"Retail Buyer","gender":"female","common_risks":["travel","stress"],"nutrient_risks":["magnesium"]},
    {"id":428,"job":"Store Planner","gender":"female","common_risks":["sedentary"],"nutrient_risks":["vitamin D"]},
    {"id":429,"job":"Visual Merchandiser","gender":"female","common_risks":["standing"],"nutrient_risks":["magnesium"]},
    {"id":430,"job":"Shop Window Designer","gender":"female","common_risks":["standing"],"nutrient_risks":["magnesium"]},
    {"id":431,"job":"Market Research Analyst","gender":"female","common_risks":["sedentary"],"nutrient_risks":["vitamin D"]},
    {"id":432,"job":"Consumer Insights Analyst","gender":"female","common_risks":["sedentary"],"nutrient_risks":["vitamin D"]},
    {"id":433,"job":"Brand Researcher","gender":"female","common_risks":["screen exposure"],"nutrient_risks":["omega-3"]},
    {"id":434,"job":"Trend Forecaster","gender":"female","common_risks":["screen exposure"],"nutrient_risks":["omega-3"]},
    {"id":435,"job":"Innovation Consultant","gender":"female","common_risks":["stress"],"nutrient_risks":["magnesium"]},
    {"id":436,"job":"Startup Mentor","gender":"female","common_risks":["stress"],"nutrient_risks":["magnesium"]},
    {"id":437,"job":"Venture Capital Analyst","gender":"female","common_risks":["sedentary","stress"],"nutrient_risks":["magnesium"]},
    {"id":438,"job":"Angel Investor","gender":"female","common_risks":["stress"],"nutrient_risks":["magnesium"]},
    {"id":439,"job":"Crowdfunding Consultant","gender":"female","common_risks":["stress"],"nutrient_risks":["magnesium"]},
    {"id":440,"job":"Fintech Advisor","gender":"female","common_risks":["screen exposure"],"nutrient_risks":["omega-3"]},
    {"id":441,"job":"Blockchain Analyst","gender":"female","common_risks":["screen exposure"],"nutrient_risks":["omega-3"]},
    {"id":442,"job":"Crypto Market Analyst","gender":"female","common_risks":["screen exposure"],"nutrient_risks":["omega-3"]},
    {"id":443,"job":"Digital Asset Manager","gender":"female","common_risks":["screen exposure"],"nutrient_risks":["omega-3"]},
    {"id":444,"job":"Fintech Product Manager","gender":"female","common_risks":["stress"],"nutrient_risks":["magnesium"]},
    {"id":445,"job":"Payment Systems Specialist","gender":"female","common_risks":["screen exposure"],"nutrient_risks":["omega-3"]},
    {"id":446,"job":"Fraud Analyst","gender":"female","common_risks":["stress"],"nutrient_risks":["magnesium"]},
    {"id":447,"job":"Risk Manager","gender":"female","common_risks":["stress"],"nutrient_risks":["magnesium"]},
    {"id":448,"job":"Compliance Officer","gender":"female","common_risks":["sedentary","stress"],"nutrient_risks":["magnesium"]},
    {"id":449,"job":"Internal Auditor","gender":"female","common_risks":["sedentary"],"nutrient_risks":["vitamin D"]},
    {"id":450,"job":"Corporate Trainer","gender":"female","common_risks":["travel","standing"],"nutrient_risks":["magnesium"]},
    {"id":451,"job":"Leadership Coach","gender":"female","common_risks":["stress"],"nutrient_risks":["magnesium"]},
    {"id":452,"job":"Motivational Speaker","gender":"female","common_risks":["travel","stress"],"nutrient_risks":["magnesium"]},
    {"id":453,"job":"Public Speaker","gender":"female","common_risks":["stress"],"nutrient_risks":["magnesium"]},
    {"id":454,"job":"Debate Coach","gender":"female","common_risks":["stress"],"nutrient_risks":["magnesium"]},
    {"id":455,"job":"Media Trainer","gender":"female","common_risks":["stress"],"nutrient_risks":["magnesium"]},
    {"id":456,"job":"Communication Coach","gender":"female","common_risks":["stress"],"nutrient_risks":["magnesium"]},
    {"id":457,"job":"Negotiation Trainer","gender":"female","common_risks":["stress"],"nutrient_risks":["magnesium"]},
    {"id":458,"job":"Conflict Mediator","gender":"female","common_risks":["emotional stress"],"nutrient_risks":["magnesium"]},
    {"id":459,"job":"Crisis Counselor","gender":"female","common_risks":["emotional stress"],"nutrient_risks":["magnesium"]},
    {"id":460,"job":"Disaster Relief Worker","gender":"female","common_risks":["stress","travel"],"nutrient_risks":["magnesium"]},
    {"id":461,"job":"Emergency Response Coordinator","gender":"female","common_risks":["stress"],"nutrient_risks":["magnesium"]},
    {"id":462,"job":"Safety Trainer","gender":"female","common_risks":["standing"],"nutrient_risks":["magnesium"]},
    {"id":463,"job":"Workplace Safety Officer","gender":"female","common_risks":["stress"],"nutrient_risks":["magnesium"]},
    {"id":464,"job":"Ergonomics Consultant","gender":"female","common_risks":["sedentary"],"nutrient_risks":["vitamin D"]},
    {"id":465,"job":"Corporate Wellness Manager","gender":"female","common_risks":["stress"],"nutrient_risks":["magnesium"]},
    {"id":466,"job":"Employee Experience Manager","gender":"female","common_risks":["stress"],"nutrient_risks":["magnesium"]},
    {"id":467,"job":"Diversity and Inclusion Officer","gender":"female","common_risks":["stress"],"nutrient_risks":["magnesium"]},
    {"id":468,"job":"Organizational Psychologist","gender":"female","common_risks":["stress"],"nutrient_risks":["magnesium"]},
    {"id":469,"job":"HR Development Specialist","gender":"female","common_risks":["sedentary"],"nutrient_risks":["vitamin D"]},
    {"id":470,"job":"Talent Development Manager","gender":"female","common_risks":["stress"],"nutrient_risks":["magnesium"]},
    {"id":471,"job":"Learning and Development Manager","gender":"female","common_risks":["stress"],"nutrient_risks":["magnesium"]},
    {"id":472,"job":"Employee Engagement Manager","gender":"female","common_risks":["stress"],"nutrient_risks":["magnesium"]},
    {"id":473,"job":"Corporate Culture Manager","gender":"female","common_risks":["stress"],"nutrient_risks":["magnesium"]},
    {"id":474,"job":"People Operations Manager","gender":"female","common_risks":["stress"],"nutrient_risks":["magnesium"]},
    {"id":475,"job":"Workforce Analyst","gender":"female","common_risks":["sedentary"],"nutrient_risks":["vitamin D"]},
    {"id":476,"job":"Remote Work Consultant","gender":"female","common_risks":["sedentary"],"nutrient_risks":["vitamin D"]},
    {"id":477,"job":"Freelance Consultant","gender":"female","common_risks":["stress"],"nutrient_risks":["magnesium"]},
    {"id":478,"job":"Independent Researcher","gender":"female","common_risks":["sedentary"],"nutrient_risks":["vitamin D"]},
    {"id":479,"job":"Think Tank Analyst","gender":"female","common_risks":["sedentary"],"nutrient_risks":["vitamin D"]},
    {"id":480,"job":"Strategic Advisor","gender":"female","common_risks":["stress"],"nutrient_risks":["magnesium"]},
    {"id":481,"job":"Corporate Board Member","gender":"female","common_risks":["stress"],"nutrient_risks":["magnesium"]},
    {"id":482,"job":"Nonprofit Board Member","gender":"female","common_risks":["stress"],"nutrient_risks":["magnesium"]},
    {"id":483,"job":"Ethics Advisor","gender":"female","common_risks":["stress"],"nutrient_risks":["magnesium"]},
    {"id":484,"job":"Governance Specialist","gender":"female","common_risks":["sedentary"],"nutrient_risks":["vitamin D"]},
    {"id":485,"job":"Policy Consultant","gender":"female","common_risks":["sedentary","stress"],"nutrient_risks":["magnesium"]},
    {"id":486,"job":"Economic Advisor","gender":"female","common_risks":["sedentary"],"nutrient_risks":["vitamin D"]},
    {"id":487,"job":"International Trade Analyst","gender":"female","common_risks":["travel"],"nutrient_risks":["magnesium"]},
    {"id":488,"job":"Global Business Consultant","gender":"female","common_risks":["travel","stress"],"nutrient_risks":["magnesium"]},
    {"id":489,"job":"Export Manager","gender":"female","common_risks":["travel"],"nutrient_risks":["magnesium"]},
    {"id":490,"job":"Import Coordinator","gender":"female","common_risks":["stress"],"nutrient_risks":["magnesium"]},
    {"id":491,"job":"Shipping Coordinator","gender":"female","common_risks":["stress"],"nutrient_risks":["magnesium"]},
    {"id":492,"job":"Freight Forwarding Agent","gender":"female","common_risks":["stress"],"nutrient_risks":["magnesium"]},
    {"id":493,"job":"Port Operations Manager","gender":"female","common_risks":["stress"],"nutrient_risks":["magnesium"]},
    {"id":494,"job":"Airport Operations Staff","gender":"female","common_risks":["shift work"],"nutrient_risks":["magnesium"]},
    {"id":495,"job":"Airline Operations Coordinator","gender":"female","common_risks":["shift work"],"nutrient_risks":["magnesium"]},
    {"id":496,"job":"Transportation Planner","gender":"female","common_risks":["sedentary"],"nutrient_risks":["vitamin D"]},
    {"id":497,"job":"Mobility Consultant","gender":"female","common_risks":["travel"],"nutrient_risks":["magnesium"]},
    {"id":498,"job":"Smart City Planner","gender":"female","common_risks":["sedentary"],"nutrient_risks":["vitamin D"]},
    {"id":499,"job":"Urban Mobility Analyst","gender":"female","common_risks":["sedentary"],"nutrient_risks":["vitamin D"]},
    {"id":500,"job":"Future of Work Researcher","gender":"female","common_risks":["sedentary"],"nutrient_risks":["vitamin D"]}
  ]
}
